[
  {
    "name": "Luna",
    "surname": "Sarmiento",
    "e-mail": "luna942008@hotmail.it",
    "birth-date": "04-08-1999",
    "avatar": "https://upload.wikimedia.org/wikipedia/commons/thumb/e/e1/FullMoon2010.jpg/260px-FullMoon2010.jpg",
    "id": "fm0bym3u4ksg3qfi8"
  },
  {
    "name": "Luna",
    "surname": "Sarmiento",
    "e-mail": "selene942008@hotmail.com",
    "birth-date": "04-08-1999",
    "avatar": "https://upload.wikimedia.org/wikipedia/commons/thumb/e/e1/FullMoon2010.jpg/260px-FullMoon2010.jpg",
    "id": "123456"
  }
]
